Metadata-Version: 2.1
Name: mammoth-nlp
Version: 0.2.1
Summary: Massively Multilingual Modular Open Translation @ Helsinki
Project-URL: Documentation, https://helsinki-nlp.github.io/mammoth/
Project-URL: Source, https://github.com/Helsinki-NLP/mammoth
Requires-Python: >=3.5
License-File: LICENSE.md
Requires-Dist: configargparse
Requires-Dist: einops (==0.8.0)
Requires-Dist: flake8 (==4.0.1)
Requires-Dist: flask (==2.0.3)
Requires-Dist: pyonmttok (<2,>=1.32)
Requires-Dist: pytest-flake8 (==1.1.1)
Requires-Dist: pytest (==7.0.1)
Requires-Dist: pyyaml
Requires-Dist: sacrebleu (==2.3.1)
Requires-Dist: scikit-learn (==1.2.0)
Requires-Dist: sentencepiece (==0.1.97)
Requires-Dist: tensorboard (>=2.9)
Requires-Dist: timeout-decorator
Requires-Dist: torch (>=1.10.2)
Requires-Dist: tqdm (==4.66.2)
Requires-Dist: waitress
Requires-Dist: x-transformers (==1.32.14)
